project/rtl/led_test.v
module	led_test
(
	input	wire		sys_clk		,
	input	wire		sys_rst_n	,
	
	
	output	wire		o_led		
	
);

reg		[9:0]	cnt_test = 'd0;
always@(posedge sys_clk) begin
	if(sys_rst_n == 'd0) begin
		cnt_test	<=	'd0;
	end
	else begin
		cnt_test	<=	cnt_test + 'd1;
	end
end





assign	o_led = cnt_test[9];



endmodule

project/tb/tb_led_test.v

`timescale 1ns / 1ps
module tb_led_test;

reg        sys_clk;
reg        sys_rst_n;
wire       o_led;

led_test u_dut (
    .sys_clk    (sys_clk),
    .sys_rst_n  (sys_rst_n),
    .o_led      (o_led)
);

initial sys_clk = 0;
always #10 sys_clk = ~sys_clk;

initial begin
    $dumpfile("../sim/wave.vcd");
    $dumpvars(0, tb_led_test);

    sys_rst_n = 0;
    #50 sys_rst_n = 1;
    #2000;
    $display("Simulation finished.");
    $finish;
end

endmodule

project/sim/wave.vcd
$date
	Mon Jul  6 05:47:36 2026
$end
$version
	Icarus Verilog
$end
$timescale
	1ps
$end
$scope module tb_led_test $end
$var wire 1 ! o_led $end
$var reg 1 " sys_clk $end
$var reg 1 # sys_rst_n $end
$scope module u_dut $end
$var wire 1 " sys_clk $end
$var wire 1 # sys_rst_n $end
$var wire 1 ! o_led $end
$var reg 10 $ cnt_test [9:0] $end
$upscope $end
$upscope $end
$enddefinitions $end
$comment Show the parameter values. $end
$dumpall
$end
#0
$dumpvars
b0 $
0#
0"
0!
$end
#10000
1"
#20000
0"
#30000
1"
#40000
0"
#50000
b1 $
1"
1#
#60000
0"
#70000
b10 $
1"
#80000
0"
#90000
b11 $
1"
#100000
0"
#110000
b100 $
1"
#120000
0"
#130000
b101 $
1"
#140000
0"
#150000
b110 $
1"
#160000
0"
#170000
b111 $
1"
#180000
0"
#190000
b1000 $
1"
#200000
0"
#210000
b1001 $
1"
#220000
0"
#230000
b1010 $
1"
#240000
0"
#250000
b1011 $
1"
#260000
0"
#270000
b1100 $
1"
#280000
0"
#290000
b1101 $
1"
#300000
0"
#310000
b1110 $
1"
#320000
0"
#330000
b1111 $
1"
#340000
0"
#350000
b10000 $
1"
#360000
0"
#370000
b10001 $
1"
#380000
0"
#390000
b10010 $
1"
#400000
0"
#410000
b10011 $
1"
#420000
0"
#430000
b10100 $
1"
#440000
0"
#450000
b10101 $
1"
#460000
0"
#470000
b10110 $
1"
#480000
0"
#490000
b10111 $
1"
#500000
0"
#510000
b11000 $
1"
#520000
0"
#530000
b11001 $
1"
#540000
0"
#550000
b11010 $
1"
#560000
0"
#570000
b11011 $
1"
#580000
0"
#590000
b11100 $
1"
#600000
0"
#610000
b11101 $
1"
#620000
0"
#630000
b11110 $
1"
#640000
0"
#650000
b11111 $
1"
#660000
0"
#670000
b100000 $
1"
#680000
0"
#690000
b100001 $
1"
#700000
0"
#710000
b100010 $
1"
#720000
0"
#730000
b100011 $
1"
#740000
0"
#750000
b100100 $
1"
#760000
0"
#770000
b100101 $
1"
#780000
0"
#790000
b100110 $
1"
#800000
0"
#810000
b100111 $
1"
#820000
0"
#830000
b101000 $
1"
#840000
0"
#850000
b101001 $
1"
#860000
0"
#870000
b101010 $
1"
#880000
0"
#890000
b101011 $
1"
#900000
0"
#910000
b101100 $
1"
#920000
0"
#930000
b101101 $
1"
#940000
0"
#950000
b101110 $
1"
#960000
0"
#970000
b101111 $
1"
#980000
0"
#990000
b110000 $
1"
#1000000
0"
#1010000
b110001 $
1"
#1020000
0"
#1030000
b110010 $
1"
#1040000
0"
#1050000
b110011 $
1"
#1060000
0"
#1070000
b110100 $
1"
#1080000
0"
#1090000
b110101 $
1"
#1100000
0"
#1110000
b110110 $
1"
#1120000
0"
#1130000
b110111 $
1"
#1140000
0"
#1150000
b111000 $
1"
#1160000
0"
#1170000
b111001 $
1"
#1180000
0"
#1190000
b111010 $
1"
#1200000
0"
#1210000
b111011 $
1"
#1220000
0"
#1230000
b111100 $
1"
#1240000
0"
#1250000
b111101 $
1"
#1260000
0"
#1270000
b111110 $
1"
#1280000
0"
#1290000
b111111 $
1"
#1300000
0"
#1310000
b1000000 $
1"
#1320000
0"
#1330000
b1000001 $
1"
#1340000
0"
#1350000
b1000010 $
1"
#1360000
0"
#1370000
b1000011 $
1"
#1380000
0"
#1390000
b1000100 $
1"
#1400000
0"
#1410000
b1000101 $
1"
#1420000
0"
#1430000
b1000110 $
1"
#1440000
0"
#1450000
b1000111 $
1"
#1460000
0"
#1470000
b1001000 $
1"
#1480000
0"
#1490000
b1001001 $
1"
#1500000
0"
#1510000
b1001010 $
1"
#1520000
0"
#1530000
b1001011 $
1"
#1540000
0"
#1550000
b1001100 $
1"
#1560000
0"
#1570000
b1001101 $
1"
#1580000
0"
#1590000
b1001110 $
1"
#1600000
0"
#1610000
b1001111 $
1"
#1620000
0"
#1630000
b1010000 $
1"
#1640000
0"
#1650000
b1010001 $
1"
#1660000
0"
#1670000
b1010010 $
1"
#1680000
0"
#1690000
b1010011 $
1"
#1700000
0"
#1710000
b1010100 $
1"
#1720000
0"
#1730000
b1010101 $
1"
#1740000
0"
#1750000
b1010110 $
1"
#1760000
0"
#1770000
b1010111 $
1"
#1780000
0"
#1790000
b1011000 $
1"
#1800000
0"
#1810000
b1011001 $
1"
#1820000
0"
#1830000
b1011010 $
1"
#1840000
0"
#1850000
b1011011 $
1"
#1860000
0"
#1870000
b1011100 $
1"
#1880000
0"
#1890000
b1011101 $
1"
#1900000
0"
#1910000
b1011110 $
1"
#1920000
0"
#1930000
b1011111 $
1"
#1940000
0"
#1950000
b1100000 $
1"
#1960000
0"
#1970000
b1100001 $
1"
#1980000
0"
#1990000
b1100010 $
1"
#2000000
0"
#2010000
b1100011 $
1"
#2020000
0"
#2030000
b1100100 $
1"
#2040000
0"
#2050000
b1100101 $
1"
